bruco/__init__.py
bruco/__main__.py
bruco/coherence.py
bruco/functions.py
bruco/ligodata.py
bruco/parameters.py
bruco/report.py
bruco/html/__init__.py
bruco/html/markup.py
bruco-0.2.3.data/data/share/bruco/asc_modulations.txt
bruco-0.2.3.data/data/share/bruco/excluded_channels.txt
bruco-0.2.3.data/data/share/bruco/lho_cal_deltal_calibration.txt
bruco-0.2.3.data/data/share/bruco/lho_excluded_channels_O3.txt
bruco-0.2.3.data/data/share/bruco/lho_excluded_channels_O4.txt
bruco-0.2.3.data/data/share/bruco/llo_excluded_channels.txt
bruco-0.2.3.data/scripts/bruco
bruco-0.2.3.dist-info/LICENSE
bruco-0.2.3.dist-info/METADATA
bruco-0.2.3.dist-info/WHEEL
bruco-0.2.3.dist-info/top_level.txt
bruco-0.2.3.dist-info/RECORD
